ews_core_config/__init__.py
ews_core_config/config.py
ews_core_config/schema.py
ews_core_config/version.py
ews_core_config/cli/entry.py
ews_core_config-20240416.dist-info/LICENSE
ews_core_config-20240416.dist-info/METADATA
ews_core_config-20240416.dist-info/WHEEL
ews_core_config-20240416.dist-info/entry_points.txt
ews_core_config-20240416.dist-info/top_level.txt
ews_core_config-20240416.dist-info/RECORD
