Metadata-Version: 2.1
Name: ews-core-config
Version: 20240416
Summary: A simple TOML configuration for EWS settings
Author-email: EWS Consulting <github@ews-consulting.com>
License: MIT License
Project-URL: Homepage, https://github.com/EWS-Consulting-Private/ews-core-config
Project-URL: Source, https://github.com/EWS-Consulting-Private/ews-core-config
Project-URL: Documentation, https://mb.ews.tools/ews-core-config
Keywords: configuration,settings,EWS
Classifier: License :: OSI Approved :: MIT License
Classifier: Programming Language :: Python
Classifier: Programming Language :: Python :: 3.9
Classifier: Programming Language :: Python :: 3.10
Classifier: Programming Language :: Python :: 3.11
Classifier: Programming Language :: Python :: 3.12
Requires-Python: >=3.9
License-File: LICENSE
Requires-Dist: pydantic-settings[toml]
Requires-Dist: tomlkit
Requires-Dist: packaging
Provides-Extra: cli
Requires-Dist: click ; extra == 'cli'
